drf_display_integer_choice_field/__init__.py
drf_display_integer_choice_field-0.0.3.dist-info/LICENSE
drf_display_integer_choice_field-0.0.3.dist-info/METADATA
drf_display_integer_choice_field-0.0.3.dist-info/WHEEL
drf_display_integer_choice_field-0.0.3.dist-info/top_level.txt
drf_display_integer_choice_field-0.0.3.dist-info/RECORD
